chewie/auth_8021x.py
chewie/chewie.py
chewie/eap.py
chewie/ethernet_packet.py
chewie/event.py
chewie/mac_address.py
chewie/message_parser.py
chewie/state_machine.py
chewie/timer.py
chewie-0.0.2.dist-info/LICENSE.txt
chewie-0.0.2.dist-info/METADATA
chewie-0.0.2.dist-info/RECORD
chewie-0.0.2.dist-info/WHEEL
chewie-0.0.2.dist-info/top_level.txt
